nicegpt/__init__.py
nicegpt/nicegpt.py
nicegpt-0.0.7.dist-info/LICENSE
nicegpt-0.0.7.dist-info/METADATA
nicegpt-0.0.7.dist-info/WHEEL
nicegpt-0.0.7.dist-info/top_level.txt
nicegpt-0.0.7.dist-info/RECORD
