Metadata-Version: 2.1
Name: nicegpt
Version: 0.0.7
Summary: A simple package to make GPT API usage easier
Author-email: Samuel Reeder <samuel.reeder@mail.utoronto.ca>
License: MIT License
Project-URL: Homepage, https://github.com/SamuelReeder/nicegpt
Project-URL: Bug Tracker, https://github.com/SamuelReeder/nicegpt/issues
Keywords: gpt, openai, chatbot, nlp, ai, natural language processing, gpt-3, gpt-4
Classifier: Programming Language :: Python :: 3
Classifier: License :: OSI Approved :: MIT License
Classifier: Operating System :: OS Independent
Requires-Python: >=3.7
License-File: LICENSE
Requires-Dist: openai
